cqrs_framing/__init__.py
cqrs_framing/broker.py
cqrs_framing/cancellation.py
cqrs_framing/context.py
cqrs_framing/decorators.py
cqrs_framing/dispatcher.py
cqrs_framing/domain.py
cqrs_framing/events.py
cqrs_framing/handlers.py
cqrs_framing/messages.py
cqrs_framing/pipeline.py
cqrs_framing/py.typed
cqrs_framing/registry.py
cqrs_framing/responses.py
cqrs_framing-0.1.1.dist-info/licenses/LICENSE
cqrs_framing-0.1.1.dist-info/METADATA
cqrs_framing-0.1.1.dist-info/WHEEL
cqrs_framing-0.1.1.dist-info/top_level.txt
cqrs_framing-0.1.1.dist-info/RECORD
