Metadata-Version: 2.4
Name: cqrs-framing
Version: 0.1.1
Summary: Python CQRS + Domain Events Framework inspired by CommandQuery.Framing
Author: CQRS Framing Maintainers
License: MIT License
Keywords: cqrs,domain-events,command-query,ddd,event-driven
Classifier: Development Status :: 3 - Alpha
Classifier: Intended Audience :: Developers
Classifier: License :: OSI Approved :: MIT License
Classifier: Programming Language :: Python :: 3
Classifier: Programming Language :: Python :: 3.10
Classifier: Programming Language :: Python :: 3.11
Classifier: Programming Language :: Python :: 3.12
Classifier: Topic :: Software Development :: Libraries :: Application Frameworks
Requires-Python: >=3.10
License-File: LICENSE
Requires-Dist: di-done-right>=0.1.0
Dynamic: license-file
